Metadata-Version: 2.1
Name: fastplm
Version: 1.0.0
Summary: The FastPLM
Home-page: https://github.com/autoliuweijie/FastPLM
Author: Weijie Liu
Author-email: dataliu@pku.edu.cn
License: UNKNOWN
Platform: UNKNOWN
Classifier: Programming Language :: Python :: 3
Classifier: License :: OSI Approved :: MIT License
Classifier: Operating System :: OS Independent
Requires-Python: >=3.4
Requires-Dist: torch (>=1.0.0)
